relations_pymysql.py
relations_pymysql-0.6.12.dist-info/LICENSE.txt
relations_pymysql-0.6.12.dist-info/METADATA
relations_pymysql-0.6.12.dist-info/WHEEL
relations_pymysql-0.6.12.dist-info/top_level.txt
relations_pymysql-0.6.12.dist-info/RECORD
