Metadata-Version: 2.1
Name: relations-pymysql
Version: 0.6.12
Summary: DB Modeling for MySQL using the PyMySQL library
Home-page: https://github.com/relations-dil/python-relations-pymysql
Author: Gaffer Fitch
Author-email: relations@gaf3.com
Classifier: Programming Language :: Python :: 3
Classifier: License :: OSI Approved :: MIT License
License-File: LICENSE.txt
Requires-Dist: PyMySQL (==0.10.0)
Requires-Dist: relations-dil (>=0.6.12)
Requires-Dist: relations-mysql (>=0.6.3)
